CHANGES.txt
CONTRIBUTORS.txt
COPYRIGHT.txt
LICENSE.txt
MANIFEST.in
README.txt
bootstrap-buildout.py
buildout.cfg
rtd.txt
setup.cfg
setup.py
tox.ini
venusian/__init__.py
venusian/advice.py
venusian/compat/__init__.py
venusian/compat/pkgutil_26.py
venusian/tests/__init__.py
venusian/tests/test_advice.py
venusian/tests/test_venusian.py
venusian/tests/fixtures/__init__.py
venusian/tests/fixtures/category.py
venusian/tests/fixtures/classdecorator.py
venusian/tests/fixtures/inheritance.py
venusian/tests/fixtures/lifting1.py
venusian/tests/fixtures/lifting2.py
venusian/tests/fixtures/lifting3.py
venusian/tests/fixtures/lifting4.py
venusian/tests/fixtures/lifting5.py
venusian/tests/fixtures/subclassing.py
venusian/tests/fixtures/attrerror/__init__.py
venusian/tests/fixtures/attrerror/will_cause_import_error.py
venusian/tests/fixtures/attrerror_package/__init__.py
venusian/tests/fixtures/attrerror_package/will_cause_import_error/__init__.py
venusian/tests/fixtures/import_and_scan/__init__.py
venusian/tests/fixtures/import_and_scan/one.py
venusian/tests/fixtures/import_and_scan/two.py
venusian/tests/fixtures/importerror/__init__.py
venusian/tests/fixtures/importerror/will_cause_import_error.py
venusian/tests/fixtures/importerror_package/__init__.py
venusian/tests/fixtures/importerror_package/will_cause_import_error/__init__.py
venusian/tests/fixtures/importonly/__init__.py
venusian/tests/fixtures/importonly/one.py
venusian/tests/fixtures/importonly/two.py
venusian/tests/fixtures/nested/__init__.py
venusian/tests/fixtures/nested/sub1/__init__.py
venusian/tests/fixtures/nested/sub1/subsub1/__init__.py
venusian/tests/fixtures/nested/sub2/__init__.py
venusian/tests/fixtures/nested/sub2/subsub2/__init__.py
venusian/tests/fixtures/one/__init__.py
venusian/tests/fixtures/one/module.py
venusian/tests/fixtures/one/module2.py
venusian/tests/fixtures/pyc/__init__.py
venusian/tests/fixtures/pyc/module.py
venusian/tests/fixtures/pyc/subpackage/__init__.py
venusifork.egg-info/PKG-INFO
venusifork.egg-info/SOURCES.txt
venusifork.egg-info/dependency_links.txt
venusifork.egg-info/entry_points.txt
venusifork.egg-info/not-zip-safe
venusifork.egg-info/requires.txt
venusifork.egg-info/top_level.txt